Workbook

Sheet Dashboard
B2: Mystic Nails Art
B3: Panel del mes
B5: Mes: | C5: ='Configuración'!C10 -> 4 | D5: Año: | E5: ='Configuración'!C9 -> 2026
B7: Citas del mes | D7: Ingresos brutos | F7: Comisiones a manicuristas | H7: Compras del mes
B8: =SUMPRODUCT((MONTH(Citas!C6:C205)=$C$5)*(YEAR(Citas!C6:C205)=$E$5)*(Citas!U6:U205="Completada")) -> 0 | D8: =SUMPRODUCT((MONTH(Citas!C6:C205)=$C$5)*(YEAR(Citas!C6:C205)=$E$5)*(Citas!U6:U205="Completada")*Citas!R6:R205) -> 0 | F8: =SUMPRODUCT((MONTH(Citas!C6:C205)=$C$5)*(YEAR(Citas!C6:C205)=$E$5)*(Citas!U6:U205="Completada")*(Citas!Z6:Z205+Citas!P6:P205)) -> 0 | H8: =SUMIFS(Compras!F6:F105,Compras!C6:C105,">="&DATE($E$5,$C$5,1),Compras!C6:C105,"<"&DATE($E$5,$C$5+1,1)) -> 0
B11: % Empresa $ | D11: % Admin $ (tu pago) | F11: Saldo neto empresa | H11: Tu pago neto (admin)
B12: =SUMPRODUCT((MONTH(Citas!C6:C205)=$C$5)*(YEAR(Citas!C6:C205)=$E$5)*(Citas!U6:U205="Completada")*Citas!AA6:AA205) -> 0 | D12: =SUMPRODUCT((MONTH(Citas!C6:C205)=$C$5)*(YEAR(Citas!C6:C205)=$E$5)*(Citas!U6:U205="Completada")*Citas!AB6:AB205) -> 0 | F12: =SUMPRODUCT((MONTH(Citas!C6:C205)=$C$5)*(YEAR(Citas!C6:C205)=$E$5)*(Citas!U6:U205="Completada")*Citas!AA6:AA205) - SUMIFS(Compras!F6:F105,Compras!C6:C105,">="&DATE($E$5,$C$5,1),Compras!C6:C105,"<"&DATE($E$5,$C$5+1,1)) -> 0 | H12: =SUMPRODUCT((MONTH(Citas!C6:C205)=$C$5)*(YEAR(Citas!C6:C205)=$E$5)*(Citas!U6:U205="Completada")*Citas!AB6:AB205) -> 0
B16: Citas próximas (próximos 7 días) | I16: Resumen del mes
B18: Fecha | C18: Hora | D18: Clienta | E18: Manicurista | F18: Servicio | G18: Estado | I18: Promedio por cita | J18: =IFERROR(D8/C8,0) -> 0
I19: Propinas del mes | J19: =SUMPRODUCT((MONTH(Citas!C6:C205)=$C$5)*(YEAR(Citas!C6:C205)=$E$5)*(Citas!U6:U205="Completada")*Citas!P6:P205) -> 0
I20: Descuentos otorgados | J20: =SUMPRODUCT((MONTH(Citas!C6:C205)=$C$5)*(YEAR(Citas!C6:C205)=$E$5)*(Citas!U6:U205="Completada")*Citas!O6:O205) -> 0
I21: Citas canceladas | J21: =SUMPRODUCT((MONTH(Citas!C6:C205)=$C$5)*(YEAR(Citas!C6:C205)=$E$5)*(Citas!U6:U205="Cancelada")) -> 0
I22: No-shows | J22: =SUMPRODUCT((MONTH(Citas!C6:C205)=$C$5)*(YEAR(Citas!C6:C205)=$E$5)*(Citas!U6:U205="No-show")) -> 0

Sheet Citas
B2: Citas y servicios
B3: Cada fila es una cita. Las celdas en gris claro se calculan solas.
B5: ID Cita | C5: Fecha | D5: Hora Inicio | E5: Duración (min) | F5: Clienta | G5: Tipo (auto) | H5: Manicurista | I5: Servicio Principal | J5: Detalle del servicio | K5: Servicios extras | L5: Precio servicio (auto) | M5: Cobro extras | N5: Subtotal (auto) | O5: Descuento | P5: Propina | Q5: Depósito | R5: Total cobrado (auto) | S5: Saldo día (auto) | T5: Método pago | U5: Estado | V5: Notas | W5: % Manicurista (auto) | X5: % Empresa (auto) | Y5: % Admin (auto) | Z5: Comisión $ (auto) | AA5: Empresa $ (auto) | AB5: Admin $ (auto) | AC5: Pago manicurista total (auto) | AD5: Foto Drive (link)
B6: CT001 | G6: {=IF(F6="","",IFERROR(INDEX(Clientas!$F$6:$F$55,MATCH(F6,Clientas!$C$6:$C$55,0)),""))} | L6: =IF(OR(I6="",J6="",G6=""),0,IF(G6="Local",SUMIFS(Servicios!$F$6:$F$39,Servicios!$D$6:$D$39,I6,Servicios!$E$6:$E$39,J6),SUMIFS(Servicios!$G$6:$G$39,Servicios!$D$6:$D$39,I6,Servicios!$E$6:$E$39,J6))) -> 0 | N6: =N(L6)+N(M6) -> 0 | R6: =N6-N(O6)+N(P6) -> 0 | S6: =R6-N(Q6) -> 0 | T6: Efectivo | U6: Completada | V6: Cliente recurrente | W6: {=IF(H6="","",IFERROR(INDEX(Manicuristas!$D$6:$D$9,MATCH(H6,Manicuristas!$C$6:$C$9,0)),0))} | X6: {=IF(H6="","",IFERROR(INDEX(Manicuristas!$E$6:$E$9,MATCH(H6,Manicuristas!$C$6:$C$9,0)),0))} | Y6: {=IF(H6="","",IFERROR(INDEX(Manicuristas!$F$6:$F$9,MATCH(H6,Manicuristas!$C$6:$C$9,0)),0))} | Z6: =IFERROR((N6-N(O6))*W6,0) -> 0 | AA6: =IFERROR((N6-N(O6))*X6,0) -> 0 | AB6: =IFERROR((N6-N(O6))*Y6,0) -> 0 | AC6: =Z6+N(P6) -> 0
B7: CT002 | G7: {=IF(F7="","",IFERROR(INDEX(Clientas!$F$6:$F$55,MATCH(F7,Clientas!$C$6:$C$55,0)),""))} | L7: =IF(OR(I7="",J7="",G7=""),0,IF(G7="Local",SUMIFS(Servicios!$F$6:$F$39,Servicios!$D$6:$D$39,I7,Servicios!$E$6:$E$39,J7),SUMIFS(Servicios!$G$6:$G$39,Servicios!$D$6:$D$39,I7,Servicios!$E$6:$E$39,J7))) -> 0 | N7: =N(L7)+N(M7) -> 0 | R7: =N7-N(O7)+N(P7) -> 0 | S7: =R7-N(Q7) -> 0 | T7: Transferencia | U7: Completada | W7: {=IF(H7="","",IFERROR(INDEX(Manicuristas!$D$6:$D$9,MATCH(H7,Manicuristas!$C$6:$C$9,0)),0))} | X7: {=IF(H7="","",IFERROR(INDEX(Manicuristas!$E$6:$E$9,MATCH(H7,Manicuristas!$C$6:$C$9,0)),0))} | Y7: {=IF(H7="","",IFERROR(INDEX(Manicuristas!$F$6:$F$9,MATCH(H7,Manicuristas!$C$6:$C$9,0)),0))} | Z7: =IFERROR((N7-N(O7))*W7,0) -> 0 | AA7: =IFERROR((N7-N(O7))*X7,0) -> 0 | AB7: =IFERROR((N7-N(O7))*Y7,0) -> 0 | AC7: =Z7+N(P7) -> 0
B8: CT003 | G8: {=IF(F8="","",IFERROR(INDEX(Clientas!$F$6:$F$55,MATCH(F8,Clientas!$C$6:$C$55,0)),""))} | L8: =IF(OR(I8="",J8="",G8=""),0,IF(G8="Local",SUMIFS(Servicios!$F$6:$F$39,Servicios!$D$6:$D$39,I8,Servicios!$E$6:$E$39,J8),SUMIFS(Servicios!$G$6:$G$39,Servicios!$D$6:$D$39,I8,Servicios!$E$6:$E$39,J8))) -> 0 | N8: =N(L8)+N(M8) -> 0 | R8: =N8-N(O8)+N(P8) -> 0 | S8: =R8-N(Q8) -> 0 | T8: Efectivo | U8: Confirmada | V8: Pidió descuento por referida | W8: {=IF(H8="","",IFERROR(INDEX(Manicuristas!$D$6:$D$9,MATCH(H8,Manicuristas!$C$6:$C$9,0)),0))} | X8: {=IF(H8="","",IFERROR(INDEX(Manicuristas!$E$6:$E$9,MATCH(H8,Manicuristas!$C$6:$C$9,0)),0))} | Y8: {=IF(H8="","",IFERROR(INDEX(Manicuristas!$F$6:$F$9,MATCH(H8,Manicuristas!$C$6:$C$9,0)),0))} | Z8: =IFERROR((N8-N(O8))*W8,0) -> 0 | AA8: =IFERROR((N8-N(O8))*X8,0) -> 0 | AB8: =IFERROR((N8-N(O8))*Y8,0) -> 0 | AC8: =Z8+N(P8) -> 0
G9: {=IF(F9="","",IFERROR(INDEX(Clientas!$F$6:$F$55,MATCH(F9,Clientas!$C$6:$C$55,0)),""))} | L9: =IF(OR(I9="",J9="",G9=""),0,IF(G9="Local",SUMIFS(Servicios!$F$6:$F$39,Servicios!$D$6:$D$39,I9,Servicios!$E$6:$E$39,J9),SUMIFS(Servicios!$G$6:$G$39,Servicios!$D$6:$D$39,I9,Servicios!$E$6:$E$39,J9))) -> 0 | N9: =N(L9)+N(M9) -> 0 | R9: =N9-N(O9)+N(P9) -> 0 | S9: =R9-N(Q9) -> 0 | W9: {=IF(H9="","",IFERROR(INDEX(Manicuristas!$D$6:$D$9,MATCH(H9,Manicuristas!$C$6:$C$9,0)),0))} | X9: {=IF(H9="","",IFERROR(INDEX(Manicuristas!$E$6:$E$9,MATCH(H9,Manicuristas!$C$6:$C$9,0)),0))} | Y9: {=IF(H9="","",IFERROR(INDEX(Manicuristas!$F$6:$F$9,MATCH(H9,Manicuristas!$C$6:$C$9,0)),0))} | Z9: =IFERROR((N9-N(O9))*W9,0) -> 0 | AA9: =IFERROR((N9-N(O9))*X9,0) -> 0 | AB9: =IFERROR((N9-N(O9))*Y9,0) -> 0 | AC9: =Z9+N(P9) -> 0
G10: {=IF(F10="","",IFERROR(INDEX(Clientas!$F$6:$F$55,MATCH(F10,Clientas!$C$6:$C$55,0)),""))} | L10: =IF(OR(I10="",J10="",G10=""),0,IF(G10="Local",SUMIFS(Servicios!$F$6:$F$39,Servicios!$D$6:$D$39,I10,Servicios!$E$6:$E$39,J10),SUMIFS(Servicios!$G$6:$G$39,Servicios!$D$6:$D$39,I10,Servicios!$E$6:$E$39,J10))) -> 0 | N10: =N(L10)+N(M10) -> 0 | R10: =N10-N(O10)+N(P10) -> 0 | S10: =R10-N(Q10) -> 0 | W10: {=IF(H10="","",IFERROR(INDEX(Manicuristas!$D$6:$D$9,MATCH(H10,Manicuristas!$C$6:$C$9,0)),0))} | X10: {=IF(H10="","",IFERROR(INDEX(Manicuristas!$E$6:$E$9,MATCH(H10,Manicuristas!$C$6:$C$9,0)),0))} | Y10: {=IF(H10="","",IFERROR(INDEX(Manicuristas!$F$6:$F$9,MATCH(H10,Manicuristas!$C$6:$C$9,0)),0))} | Z10: =IFERROR((N10-N(O10))*W10,0) -> 0 | AA10: =IFERROR((N10-N(O10))*X10,0) -> 0 | AB10: =IFERROR((N10-N(O10))*Y10,0) -> 0 | AC10: =Z10+N(P10) -> 0
G11: {=IF(F11="","",IFERROR(INDEX(Clientas!$F$6:$F$55,MATCH(F11,Clientas!$C$6:$C$55,0)),""))} | L11: =IF(OR(I11="",J11="",G11=""),0,IF(G11="Local",SUMIFS(Servicios!$F$6:$F$39,Servicios!$D$6:$D$39,I11,Servicios!$E$6:$E$39,J11),SUMIFS(Servicios!$G$6:$G$39,Servicios!$D$6:$D$39,I11,Servicios!$E$6:$E$39,J11))) -> 0 | N11: =N(L11)+N(M11) -> 0 | R11: =N11-N(O11)+N(P11) -> 0 | S11: =R11-N(Q11) -> 0 | W11: {=IF(H11="","",IFERROR(INDEX(Manicuristas!$D$6:$D$9,MATCH(H11,Manicuristas!$C$6:$C$9,0)),0))} | X11: {=IF(H11="","",IFERROR(INDEX(Manicuristas!$E$6:$E$9,MATCH(H11,Manicuristas!$C$6:$C$9,0)),0))} | Y11: {=IF(H11="","",IFERROR(INDEX(Manicuristas!$F$6:$F$9,MATCH(H11,Manicuristas!$C$6:$C$9,0)),0))} | Z11: =IFERROR((N11-N(O11))*W11,0) -> 0 | AA11: =IFERROR((N11-N(O11))*X11,0) -> 0 | AB11: =IFERROR((N11-N(O11))*Y11,0) -> 0 | AC11: =Z11+N(P11) -> 0
G12: {=IF(F12="","",IFERROR(INDEX(Clientas!$F$6:$F$55,MATCH(F12,Clientas!$C$6:$C$55,0)),""))} | L12: =IF(OR(I12="",J12="",G12=""),0,IF(G12="Local",SUMIFS(Servicios!$F$6:$F$39,Servicios!$D$6:$D$39,I12,Servicios!$E$6:$E$39,J12),SUMIFS(Servicios!$G$6:$G$39,Servicios!$D$6:$D$39,I12,Servicios!$E$6:$E$39,J12))) -> 0 | N12: =N(L12)+N(M12) -> 0 | R12: =N12-N(O12)+N(P12) -> 0 | S12: =R12-N(Q12) -> 0 | W12: {=IF(H12="","",IFERROR(INDEX(Manicuristas!$D$6:$D$9,MATCH(H12,Manicuristas!$C$6:$C$9,0)),0))} | X12: {=IF(H12="","",IFERROR(INDEX(Manicuristas!$E$6:$E$9,MATCH(H12,Manicuristas!$C$6:$C$9,0)),0))} | Y12: {=IF(H12="","",IFERROR(INDEX(Manicuristas!$F$6:$F$9,MATCH(H12,Manicuristas!$C$6:$C$9,0)),0))} | Z12: =IFERROR((N12-N(O12))*W12,0) -> 0 | AA12: =IFERROR((N12-N(O12))*X12,0) -> 0 | AB12: =IFERROR((N12-N(O12))*Y12,0) -> 0 | AC12: =Z12+N(P12) -> 0
G13: {=IF(F13="","",IFERROR(INDEX(Clientas!$F$6:$F$55,MATCH(F13,Clientas!$C$6:$C$55,0)),""))} | L13: =IF(OR(I13="",J13="",G13=""),0,IF(G13="Local",SUMIFS(Servicios!$F$6:$F$39,Servicios!$D$6:$D$39,I13,Servicios!$E$6:$E$39,J13),SUMIFS(Servicios!$G$6:$G$39,Servicios!$D$6:$D$39,I13,Servicios!$E$6:$E$39,J13))) -> 0 | N13: =N(L13)+N(M13) -> 0 | R13: =N13-N(O13)+N(P13) -> 0 | S13: =R13-N(Q13) -> 0 | W13: {=IF(H13="","",IFERROR(INDEX(Manicuristas!$D$6:$D$9,MATCH(H13,Manicuristas!$C$6:$C$9,0)),0))} | X13: {=IF(H13="","",IFERROR(INDEX(Manicuristas!$E$6:$E$9,MATCH(H13,Manicuristas!$C$6:$C$9,0)),0))} | Y13: {=IF(H13="","",IFERROR(INDEX(Manicuristas!$F$6:$F$9,MATCH(H13,Manicuristas!$C$6:$C$9,0)),0))} | Z13: =IFERROR((N13-N(O13))*W13,0) -> 0 | AA13: =IFERROR((N13-N(O13))*X13,0) -> 0 | AB13: =IFERROR((N13-N(O13))*Y13,0) -> 0 | AC13: =Z13+N(P13) -> 0
G14: {=IF(F14="","",IFERROR(INDEX(Clientas!$F$6:$F$55,MATCH(F14,Clientas!$C$6:$C$55,0)),""))} | L14: =IF(OR(I14="",J14="",G14=""),0,IF(G14="Local",SUMIFS(Servicios!$F$6:$F$39,Servicios!$D$6:$D$39,I14,Servicios!$E$6:$E$39,J14),SUMIFS(Servicios!$G$6:$G$39,Servicios!$D$6:$D$39,I14,Servicios!$E$6:$E$39,J14))) -> 0 | N14: =N(L14)+N(M14) -> 0 | R14: =N14-N(O14)+N(P14) -> 0 | S14: =R14-N(Q14) -> 0 | W14: {=IF(H14="","",IFERROR(INDEX(Manicuristas!$D$6:$D$9,MATCH(H14,Manicuristas!$C$6:$C$9,0)),0))} | X14: {=IF(H14="","",IFERROR(INDEX(Manicuristas!$E$6:$E$9,MATCH(H14,Manicuristas!$C$6:$C$9,0)),0))} | Y14: {=IF(H14="","",IFERROR(INDEX(Manicuristas!$F$6:$F$9,MATCH(H14,Manicuristas!$C$6:$C$9,0)),0))} | Z14: =IFERROR((N14-N(O14))*W14,0) -> 0 | AA14: =IFERROR((N14-N(O14))*X14,0) -> 0 | AB14: =IFERROR((N14-N(O14))*Y14,0) -> 0 | AC14: =Z14+N(P14) -> 0
G15: {=IF(F15="","",IFERROR(INDEX(Clientas!$F$6:$F$55,MATCH(F15,Clientas!$C$6:$C$55,0)),""))} | L15: =IF(OR(I15="",J15="",G15=""),0,IF(G15="Local",SUMIFS(Servicios!$F$6:$F$39,Servicios!$D$6:$D$39,I15,Servicios!$E$6:$E$39,J15),SUMIFS(Servicios!$G$6:$G$39,Servicios!$D$6:$D$39,I15,Servicios!$E$6:$E$39,J15))) -> 0 | N15: =N(L15)+N(M15) -> 0 | R15: =N15-N(O15)+N(P15) -> 0 | S15: =R15-N(Q15) -> 0 | W15: {=IF(H15="","",IFERROR(INDEX(Manicuristas!$D$6:$D$9,MATCH(H15,Manicuristas!$C$6:$C$9,0)),0))} | X15: {=IF(H15="","",IFERROR(INDEX(Manicuristas!$E$6:$E$9,MATCH(H15,Manicuristas!$C$6:$C$9,0)),0))} | Y15: {=IF(H15="","",IFERROR(INDEX(Manicuristas!$F$6:$F$9,MATCH(H15,Manicuristas!$C$6:$C$9,0)),0))} | Z15: =IFERROR((N15-N(O15))*W15,0) -> 0 | AA15: =IFERROR((N15-N(O15))*X15,0) -> 0 | AB15: =IFERROR((N15-N(O15))*Y15,0) -> 0 | AC15: =Z15+N(P15) -> 0
G16: {=IF(F16="","",IFERROR(INDEX(Clientas!$F$6:$F$55,MATCH(F16,Clientas!$C$6:$C$55,0)),""))} | L16: =IF(OR(I16="",J16="",G16=""),0,IF(G16="Local",SUMIFS(Servicios!$F$6:$F$39,Servicios!$D$6:$D$39,I16,Servicios!$E$6:$E$39,J16),SUMIFS(Servicios!$G$6:$G$39,Servicios!$D$6:$D$39,I16,Servicios!$E$6:$E$39,J16))) -> 0 | N16: =N(L16)+N(M16) -> 0 | R16: =N16-N(O16)+N(P16) -> 0 | S16: =R16-N(Q16) -> 0 | W16: {=IF(H16="","",IFERROR(INDEX(Manicuristas!$D$6:$D$9,MATCH(H16,Manicuristas!$C$6:$C$9,0)),0))} | X16: {=IF(H16="","",IFERROR(INDEX(Manicuristas!$E$6:$E$9,MATCH(H16,Manicuristas!$C$6:$C$9,0)),0))} | Y16: {=IF(H16="","",IFERROR(INDEX(Manicuristas!$F$6:$F$9,MATCH(H16,Manicuristas!$C$6:$C$9,0)),0))} | Z16: =IFERROR((N16-N(O16))*W16,0) -> 0 | AA16: =IFERROR((N16-N(O16))*X16,0) -> 0 | AB16: =IFERROR((N16-N(O16))*Y16,0) -> 0 | AC16: =Z16+N(P16) -> 0
G17: {=IF(F17="","",IFERROR(INDEX(Clientas!$F$6:$F$55,MATCH(F17,Clientas!$C$6:$C$55,0)),""))} | L17: =IF(OR(I17="",J17="",G17=""),0,IF(G17="Local",SUMIFS(Servicios!$F$6:$F$39,Servicios!$D$6:$D$39,I17,Servicios!$E$6:$E$39,J17),SUMIFS(Servicios!$G$6:$G$39,Servicios!$D$6:$D$39,I17,Servicios!$E$6:$E$39,J17))) -> 0 | N17: =N(L17)+N(M17) -> 0 | R17: =N17-N(O17)+N(P17) -> 0 | S17: =R17-N(Q17) -> 0 | W17: {=IF(H17="","",IFERROR(INDEX(Manicuristas!$D$6:$D$9,MATCH(H17,Manicuristas!$C$6:$C$9,0)),0))} | X17: {=IF(H17="","",IFERROR(INDEX(Manicuristas!$E$6:$E$9,MATCH(H17,Manicuristas!$C$6:$C$9,0)),0))} | Y17: {=IF(H17="","",IFERROR(INDEX(Manicuristas!$F$6:$F$9,MATCH(H17,Manicuristas!$C$6:$C$9,0)),0))} | Z17: =IFERROR((N17-N(O17))*W17,0) -> 0 | AA17: =IFERROR((N17-N(O17))*X17,0) -> 0 | AB17: =IFERROR((N17-N(O17))*Y17,0) -> 0 | AC17: =Z17+N(P17) -> 0
G18: {=IF(F18="","",IFERROR(INDEX(Clientas!$F$6:$F$55,MATCH(F18,Clientas!$C$6:$C$55,0)),""))} | L18: =IF(OR(I18="",J18="",G18=""),0,IF(G18="Local",SUMIFS(Servicios!$F$6:$F$39,Servicios!$D$6:$D$39,I18,Servicios!$E$6:$E$39,J18),SUMIFS(Servicios!$G$6:$G$39,Servicios!$D$6:$D$39,I18,Servicios!$E$6:$E$39,J18))) -> 0 | N18: =N(L18)+N(M18) -> 0 | R18: =N18-N(O18)+N(P18) -> 0 | S18: =R18-N(Q18) -> 0 | W18: {=IF(H18="","",IFERROR(INDEX(Manicuristas!$D$6:$D$9,MATCH(H18,Manicuristas!$C$6:$C$9,0)),0))} | X18: {=IF(H18="","",IFERROR(INDEX(Manicuristas!$E$6:$E$9,MATCH(H18,Manicuristas!$C$6:$C$9,0)),0))} | Y18: {=IF(H18="","",IFERROR(INDEX(Manicuristas!$F$6:$F$9,MATCH(H18,Manicuristas!$C$6:$C$9,0)),0))} | Z18: =IFERROR((N18-N(O18))*W18,0) -> 0 | AA18: =IFERROR((N18-N(O18))*X18,0) -> 0 | AB18: =IFERROR((N18-N(O18))*Y18,0) -> 0 | AC18: =Z18+N(P18) -> 0
G19: {=IF(F19="","",IFERROR(INDEX(Clientas!$F$6:$F$55,MATCH(F19,Clientas!$C$6:$C$55,0)),""))} | L19: =IF(OR(I19="",J19="",G19=""),0,IF(G19="Local",SUMIFS(Servicios!$F$6:$F$39,Servicios!$D$6:$D$39,I19,Servicios!$E$6:$E$39,J19),SUMIFS(Servicios!$G$6:$G$39,Servicios!$D$6:$D$39,I19,Servicios!$E$6:$E$39,J19))) -> 0 | N19: =N(L19)+N(M19) -> 0 | R19: =N19-N(O19)+N(P19) -> 0 | S19: =R19-N(Q19) -> 0 | W19: {=IF(H19="","",IFERROR(INDEX(Manicuristas!$D$6:$D$9,MATCH(H19,Manicuristas!$C$6:$C$9,0)),0))} | X19: {=IF(H19="","",IFERROR(INDEX(Manicuristas!$E$6:$E$9,MATCH(H19,Manicuristas!$C$6:$C$9,0)),0))} | Y19: {=IF(H19="","",IFERROR(INDEX(Manicuristas!$F$6:$F$9,MATCH(H19,Manicuristas!$C$6:$C$9,0)),0))} | Z19: =IFERROR((N19-N(O19))*W19,0) -> 0 | AA19: =IFERROR((N19-N(O19))*X19,0) -> 0 | AB19: =IFERROR((N19-N(O19))*Y19,0) -> 0 | AC19: =Z19+N(P19) -> 0
G20: {=IF(F20="","",IFERROR(INDEX(Clientas!$F$6:$F$55,MATCH(F20,Clientas!$C$6:$C$55,0)),""))} | L20: =IF(OR(I20="",J20="",G20=""),0,IF(G20="Local",SUMIFS(Servicios!$F$6:$F$39,Servicios!$D$6:$D$39,I20,Servicios!$E$6:$E$39,J20),SUMIFS(Servicios!$G$6:$G$39,Servicios!$D$6:$D$39,I20,Servicios!$E$6:$E$39,J20))) -> 0 | N20: =N(L20)+N(M20) -> 0 | R20: =N20-N(O20)+N(P20) -> 0 | S20: =R20-N(Q20) -> 0 | W20: {=IF(H20="","",IFERROR(INDEX(Manicuristas!$D$6:$D$9,MATCH(H20,Manicuristas!$C$6:$C$9,0)),0))} | X20: {=IF(H20="","",IFERROR(INDEX(Manicuristas!$E$6:$E$9,MATCH(H20,Manicuristas!$C$6:$C$9,0)),0))} | Y20: {=IF(H20="","",IFERROR(INDEX(Manicuristas!$F$6:$F$9,MATCH(H20,Manicuristas!$C$6:$C$9,0)),0))} | Z20: =IFERROR((N20-N(O20))*W20,0) -> 0 | AA20: =IFERROR((N20-N(O20))*X20,0) -> 0 | AB20: =IFERROR((N20-N(O20))*Y20,0) -> 0 | AC20: =Z20+N(P20) -> 0
... G205: {=IF(F205="","",IFERROR(INDEX(Clientas!$F$6:$F$55,MATCH(F205,Clientas!$C$6:$C$55,0)),""))} | L205: =IF(OR(I205="",J205="",G205=""),0,IF(G205="Local",SUMIFS(Servicios!$F$6:$F$39,Servicios!$D$6:$D$39,I205,Servicios!$E$6:$E$39,J205),SUMIFS(Servicios!$G$6:$G$39,Servicios!$D$6:$D$39,I205,Servicios!$E$6:$E$39,J205))) -> 0 | N205: =N(L205)+N(M205) -> 0 | R205: =N205-N(O205)+N(P205) -> 0 | S205: =R205-N(Q205) -> 0 | W205: {=IF(H205="","",IFERROR(INDEX(Manicuristas!$D$6:$D$9,MATCH(H205,Manicuristas!$C$6:$C$9,0)),0))} | X205: {=IF(H205="","",IFERROR(INDEX(Manicuristas!$E$6:$E$9,MATCH(H205,Manicuristas!$C$6:$C$9,0)),0))} | Y205: {=IF(H205="","",IFERROR(INDEX(Manicuristas!$F$6:$F$9,MATCH(H205,Manicuristas!$C$6:$C$9,0)),0))} | Z205: =IFERROR((N205-N(O205))*W205,0) -> 0 | AA205: =IFERROR((N205-N(O205))*X205,0) -> 0 | AB205: =IFERROR((N205-N(O205))*Y205,0) -> 0 | AC205: =Z205+N(P205) -> 0

Sheet Clientas
B2: Clientas
B3: Catálogo de clientas. Marca cada una como Local o Extranjera.
B5: ID | C5: Nombre | D5: Teléfono | E5: Instagram | F5: Tipo | G5: Cumpleaños | H5: Cómo te encontró | I5: Notas / alergias | J5: Primera visita | K5: Última visita | L5: # Visitas | M5: Total gastado

Sheet Servicios
B2: Catálogo de servicios
B3: Precios en MXN. Local = clienta de México. Extranjera = clienta de fuera.
B5: ID | C5: Categoría | D5: Servicio | E5: Detalle | F5: Precio Local | G5: Precio Extranjera | H5: Tiempo (min)
B6: S01 | C6: Uñas Naturales | D6: Gelish | E6: 1 Color | F6: 330 | G6: 430 | H6: 90
B7: S02 | C7: Uñas Naturales | D7: Gelish | E7: 1 Color + french | F7: 370 | G7: 470 | H7: 100
B8: S03 | C8: Uñas Naturales | D8: Gelish | E8: Diseño sencillo | F8: 400 | G8: 500 | H8: 120
B9: S04 | C9: Uñas Naturales | D9: Builder Gel | E9: 1 Color | F9: 420 | G9: 520 | H9: 120
B10: S05 | C10: Uñas Naturales | D10: Builder Gel | E10: 1 Color + french | F10: 450 | G10: 550 | H10: 130
B11: S06 | C11: Uñas Naturales | D11: Builder Gel | E11: Diseño libre | F11: 500 | G11: 600 | H11: 150
B12: S07 | C12: Uñas Naturales | D12: Rubber | E12: 1 Color | F12: 400 | G12: 500 | H12: 120
B13: S08 | C13: Uñas Naturales | D13: Rubber | E13: 1 Color + french | F13: 420 | G13: 520 | H13: 130
B14: S09 | C14: Uñas Naturales | D14: Rubber | E14: Diseño sencillo | F14: 440 | G14: 540 | H14: 150
B15: S10 | C15: Uñas Naturales | D15: Kapping de Polygel | E15: 1 Color | F15: 540 | G15: 640 | H15: 150
B16: S11 | C16: Uñas Naturales | D16: Kapping de Polygel | E16: 1 Color + french | F16: 580 | G16: 680 | H16: 160
B17: S12 | C17: Uñas Naturales | D17: Kapping de Polygel | E17: Efectos / diseño | F17: 610 | G17: 710 | H17: 180
... B39: S34 | C39: Extras Pies | D39: Cat eye, polvos de efecto, diseño | E39: Adicional | F39: 70 | G39: 70 | H39: 15

Sheet Manicuristas
B2: Manicuristas
B3: Edita las % de comisión y sueldo fijo cuando cambien
B5: ID | C5: Nombre | D5: % Manicurista | E5: % Empresa | F5: % Admin | G5: Sueldo Fijo Semanal | H5: Activa | I5: Notas
B6: M01 | C6: Carolina (co-owner) | D6: 0.8 | E6: 0.15 | F6: 0.05 | G6: 0 | H6: Sí | I6: Co-owner. % alta porque es socia. | J6: =D6+E6+F6 -> 1
B7: M02 | C7: Monse | D7: 0.4 | E7: 0.35 | F7: 0.25 | G7: 0 | H7: Sí | I7: Esquema estándar. | J7: =D7+E7+F7 -> 1
B8: M03 | C8: Manicurista 3 — Modelo A | D8: 0.4 | E8: 0.35 | F8: 0.25 | G8: 0 | H8: Sí | I8: Mismo esquema que Monse (sin sueldo fijo). | J8: =D8+E8+F8 -> 1
B9: M04 | C9: Manicurista 3 — Modelo B | D9: 0.25 | E9: 0.45 | F9: 0.3 | G9: 1200 | H9: No | I9: Sueldo fijo $1,200/semana + 25% comisión. Activa solo una de las dos. | J9: =D9+E9+F9 -> 1
C11: Verificación suma:

Sheet Compras
B2: Compras e inversión
B3: Gastos que restan del fondo de empresa (productos, herramientas, marketing, etc.)
B5: ID | C5: Fecha | D5: Concepto | E5: Categoría | F5: Monto | G5: Proveedor | H5: Método pago | I5: Quien compra | J5: Notas
B6: CO001
B7: CO002
B8: CO003

Sheet Liquidaciones
B2: Liquidaciones del periodo
B3: Cuánto le toca a cada manicurista en el mes seleccionado en Configuración
B5: Mes en curso: | C5: ='Configuración'!C10 -> 4 | D5: Año: | E5: ='Configuración'!C9 -> 2026
B7: Manicurista | C7: # Citas | D7: Total cobrado servicios | E7: Comisiones | F7: Propinas | G7: Sueldo fijo (mes) | H7: TOTAL A PAGAR
B8: Carolina (co-owner) | C8: 1 | D8: =SUMPRODUCT((Citas!H6:H205="Carolina (co-owner)")*(MONTH(Citas!C6:C205)=$C$5)*(YEAR(Citas!C6:C205)=$E$5)*(Citas!U6:U205="Completada")*Citas!R6:R205) -> 0 | E8: =SUMPRODUCT((Citas!H6:H205="Carolina (co-owner)")*(MONTH(Citas!C6:C205)=$C$5)*(YEAR(Citas!C6:C205)=$E$5)*(Citas!U6:U205="Completada")*Citas!Z6:Z205) -> 0 | F8: =SUMPRODUCT((Citas!H6:H205="Carolina (co-owner)")*(MONTH(Citas!C6:C205)=$C$5)*(YEAR(Citas!C6:C205)=$E$5)*(Citas!U6:U205="Completada")*Citas!P6:P205) -> 0 | G8: {=IF(INDEX(Manicuristas!H6:H9,MATCH("Carolina (co-owner)",Manicuristas!C6:C9,0))="Sí",INDEX(Manicuristas!G6:G9,MATCH("Carolina (co-owner)",Manicuristas!C6:C9,0))*4.33,0)} -> 0 | H8: =E8+F8+G8 -> 0
B9: Monse | C9: =SUMPRODUCT((Citas!H6:H205="Monse")*(MONTH(Citas!C6:C205)=$C$5)*(YEAR(Citas!C6:C205)=$E$5)*(Citas!U6:U205="Completada")) -> 0 | D9: =SUMPRODUCT((Citas!H6:H205="Monse")*(MONTH(Citas!C6:C205)=$C$5)*(YEAR(Citas!C6:C205)=$E$5)*(Citas!U6:U205="Completada")*Citas!R6:R205) -> 0 | E9: =SUMPRODUCT((Citas!H6:H205="Monse")*(MONTH(Citas!C6:C205)=$C$5)*(YEAR(Citas!C6:C205)=$E$5)*(Citas!U6:U205="Completada")*Citas!Z6:Z205) -> 0 | F9: =SUMPRODUCT((Citas!H6:H205="Monse")*(MONTH(Citas!C6:C205)=$C$5)*(YEAR(Citas!C6:C205)=$E$5)*(Citas!U6:U205="Completada")*Citas!P6:P205) -> 0 | G9: {=IF(INDEX(Manicuristas!H6:H9,MATCH("Monse",Manicuristas!C6:C9,0))="Sí",INDEX(Manicuristas!G6:G9,MATCH("Monse",Manicuristas!C6:C9,0))*4.33,0)} -> 0 | H9: =E9+F9+G9 -> 0
B10: Manicurista 3 — Modelo A | C10: =SUMPRODUCT((Citas!H6:H205="Manicurista 3 — Modelo A")*(MONTH(Citas!C6:C205)=$C$5)*(YEAR(Citas!C6:C205)=$E$5)*(Citas!U6:U205="Completada")) -> 0 | D10: =SUMPRODUCT((Citas!H6:H205="Manicurista 3 — Modelo A")*(MONTH(Citas!C6:C205)=$C$5)*(YEAR(Citas!C6:C205)=$E$5)*(Citas!U6:U205="Completada")*Citas!R6:R205) -> 0 | E10: =SUMPRODUCT((Citas!H6:H205="Manicurista 3 — Modelo A")*(MONTH(Citas!C6:C205)=$C$5)*(YEAR(Citas!C6:C205)=$E$5)*(Citas!U6:U205="Completada")*Citas!Z6:Z205) -> 0 | F10: =SUMPRODUCT((Citas!H6:H205="Manicurista 3 — Modelo A")*(MONTH(Citas!C6:C205)=$C$5)*(YEAR(Citas!C6:C205)=$E$5)*(Citas!U6:U205="Completada")*Citas!P6:P205) -> 0 | G10: {=IF(INDEX(Manicuristas!H6:H9,MATCH("Manicurista 3 — Modelo A",Manicuristas!C6:C9,0))="Sí",INDEX(Manicuristas!G6:G9,MATCH("Manicurista 3 — Modelo A",Manicuristas!C6:C9,0))*4.33,0)} -> 0 | H10: =E10+F10+G10 -> 0
B11: Manicurista 3 — Modelo B | C11: =SUMPRODUCT((Citas!H6:H205="Manicurista 3 — Modelo B")*(MONTH(Citas!C6:C205)=$C$5)*(YEAR(Citas!C6:C205)=$E$5)*(Citas!U6:U205="Completada")) -> 0 | D11: =SUMPRODUCT((Citas!H6:H205="Manicurista 3 — Modelo B")*(MONTH(Citas!C6:C205)=$C$5)*(YEAR(Citas!C6:C205)=$E$5)*(Citas!U6:U205="Completada")*Citas!R6:R205) -> 0 | E11: =SUMPRODUCT((Citas!H6:H205="Manicurista 3 — Modelo B")*(MONTH(Citas!C6:C205)=$C$5)*(YEAR(Citas!C6:C205)=$E$5)*(Citas!U6:U205="Completada")*Citas!Z6:Z205) -> 0 | F11: =SUMPRODUCT((Citas!H6:H205="Manicurista 3 — Modelo B")*(MONTH(Citas!C6:C205)=$C$5)*(YEAR(Citas!C6:C205)=$E$5)*(Citas!U6:U205="Completada")*Citas!P6:P205) -> 0 | G11: {=IF(INDEX(Manicuristas!H6:H9,MATCH("Manicurista 3 — Modelo B",Manicuristas!C6:C9,0))="Sí",INDEX(Manicuristas!G6:G9,MATCH("Manicurista 3 — Modelo B",Manicuristas!C6:C9,0))*4.33,0)} -> 0 | H11: =E11+F11+G11 -> 0
B12: TOTAL | C12: =SUM(C8:C11) -> 1 | D12: =SUM(D8:D11) -> 0 | E12: =SUM(E8:E11) -> 0 | F12: =SUM(F8:F11) -> 0 | G12: =SUM(G8:G11) -> 0 | H12: =SUM(H8:H11) -> 0

Sheet Configuración
B2: Mystic Nails Art
B3: Panel de configuración
B5: Parámetro | C5: Valor | D5: Descripción
B6: Nombre del estudio | C6: Mystic Nails Art | D6: Nombre que aparece en reportes
B7: Ubicación | C7: Playa del Carmen, México | D7: Solo informativo
B8: Moneda | C8: MXN | D8: Pesos mexicanos
B9: Año fiscal en curso | C9: 2026 | D9: Se usa en el dashboard
B10: Mes en curso | C10: 4 | D10: 1-12. Se usa en el dashboard
B11: Cuenta principal Calendar | C11: jgchavezpanduro@gmail.com | D11: Calendario donde se crean las citas
B12: Compartido con | C12: 27supercaro@gmail.com | D12: Co-owner que también ve la agenda
B13: % Propina al manicurista | C13: 1 | D13: 1.0 = 100% de la propina va a la manicurista
B14: Comisiones aplican sobre | C14: Subtotal - Descuento | D14: Base de cálculo de comisiones (sin propina)
B17: Cómo funciona
B18: 1. Cada vez que registres una cita en la hoja 'Citas', el sistema calcula automáticamente:
B19: • El precio del servicio según si la clienta es local o extranjera
B20: • Las comisiones según la manicurista que la atendió
B21: • Lo que se le debe a la manicurista, a la empresa y a admin (tú)
B23: 2. La hoja 'Liquidaciones' resume cuánto pagar a cada manicurista en el periodo.
B25: 3. La hoja 'Compras' registra todos los gastos. Restan del fondo de empresa.
B27: 4. La hoja 'Dashboard' muestra los KPIs del mes seleccionado arriba.
B29: 5. Las hojas 'Servicios' y 'Manicuristas' son catálogos. Edítalos cuando cambien precios o entre/salga personal.
